mesh2traccar/__init__.py
mesh2traccar/mesh2traccar.py
mesh2traccar/mesh2traccar.service
mesh2traccar-0.1.2.dist-info/licenses/LICENSE
mesh2traccar-0.1.2.dist-info/METADATA
mesh2traccar-0.1.2.dist-info/WHEEL
mesh2traccar-0.1.2.dist-info/entry_points.txt
mesh2traccar-0.1.2.dist-info/top_level.txt
mesh2traccar-0.1.2.dist-info/RECORD
