Metadata-Version: 2.4
Name: mesh2traccar
Version: 0.1.2
Summary: A Python application to forward Meshtastic MQTT location messages to a Traccar server
Author-email: Ilias Daradimos <judgedrid@gmail.com>
License:                     GNU GENERAL PUBLIC LICENSE
Keywords: meshtastic,traccar,mqtt,location,tracking
Classifier: Programming Language :: Python :: 3
Classifier: License :: OSI Approved :: GNU General Public License v3 (GPLv3)
Classifier: Operating System :: POSIX :: Linux
Requires-Python: >=3.8
License-File: LICENSE
Requires-Dist: paho-mqtt>=2.1.0
Requires-Dist: requests>=2.31.0
Requires-Dist: setuptools>=61.0
Dynamic: license-file
